CHANGELOG.md
LICENSE
MANIFEST.in
README.md
install.json
pyproject.toml
setup.py
wwt_jupyterlab_extension/__init__.py
wwt_jupyterlab_extension/_version.py
wwt_jupyterlab_extension.egg-info/PKG-INFO
wwt_jupyterlab_extension.egg-info/SOURCES.txt
wwt_jupyterlab_extension.egg-info/dependency_links.txt
wwt_jupyterlab_extension.egg-info/not-zip-safe
wwt_jupyterlab_extension.egg-info/top_level.txt
wwt_jupyterlab_extension/labextension/package.json
wwt_jupyterlab_extension/labextension/schemas/@wwtelescope/jupyterlab/package.json.orig
wwt_jupyterlab_extension/labextension/schemas/@wwtelescope/jupyterlab/research.json
wwt_jupyterlab_extension/labextension/static/407.9f916d1fe063a9e0b4a8.js
wwt_jupyterlab_extension/labextension/static/464.1d2272473d10aebf7c51.js
wwt_jupyterlab_extension/labextension/static/549.07d00f3907cdc6597af5.js
wwt_jupyterlab_extension/labextension/static/remoteEntry.5af107b2e4fb4c611c9b.js
wwt_jupyterlab_extension/labextension/static/style.js
wwt_jupyterlab_extension/labextension/static/third-party-licenses.json