Metadata-Version: 2.1
Name: wwt-jupyterlab-extension
Version: 1.4.0
Summary: AAS WorldWide Telescope in JupyterLab
Home-page: https://github.com/WorldWideTelescope/wwt-jupyterlab
Author: The AAS WorldWide Telescope Team
Author-email: wwt@aas.org
License: MIT
Keywords: Jupyter,JupyterLab,JupyterLab3
Platform: Linux
Platform: Mac OS X
Platform: Windows
Classifier: License :: OSI Approved :: BSD License
Classifier: Programming Language :: Python
Classifier: Programming Language :: Python :: 3
Classifier: Programming Language :: Python :: 3.6
Classifier: Programming Language :: Python :: 3.7
Classifier: Programming Language :: Python :: 3.8
Classifier: Programming Language :: Python :: 3.9
Classifier: Framework :: Jupyter
Requires-Python: >=3.6
License-File: LICENSE
